{
    "type": "object",
    "properties": {
        "transitionId": {
            "required": true,
            "type": "integer",
            "format": "int64"
        },
        "key": {
            "required": true,
            "type": "string"
        },
        "workflowName": {
            "required": true,
            "type": "string"
        },
        "workflowMode": {
            "type": "string",
            "enum": [
                "live",
                "draft"
            ]
        }
    }
}